addressvariable/__init__.py
dedupe_variable_address-1.0.0.dist-info/METADATA
dedupe_variable_address-1.0.0.dist-info/WHEEL
dedupe_variable_address-1.0.0.dist-info/top_level.txt
dedupe_variable_address-1.0.0.dist-info/RECORD
