Metadata-Version: 2.1
Name: dedupe-variable-address
Version: 1.0.0
Summary: Address variable type for dedupe
Home-page: https://github.com/datamade/dedupe-variables-address
License: The MIT License: http://www.opensource.org/licenses/mit-license.php
Requires-Dist: usaddress
Requires-Dist: parseratorvariable >=1.0.0
